cowin_api/__init__.py
cowin_api/api.py
cowin_api/base_api.py
cowin_api/constants.py
cowin_api/utils.py
CoWIN_API_by_Kunal_Kumar_Sahoo-1.0.0.dist-info/METADATA
CoWIN_API_by_Kunal_Kumar_Sahoo-1.0.0.dist-info/WHEEL
CoWIN_API_by_Kunal_Kumar_Sahoo-1.0.0.dist-info/top_level.txt
CoWIN_API_by_Kunal_Kumar_Sahoo-1.0.0.dist-info/RECORD
