Metadata-Version: 2.1
Name: CoWIN-API-by-Kunal-Kumar-Sahoo
Version: 1.0.0
Summary: Python wrapper for CoWin API developed by Kunal Kumar Sahoo
Home-page: https://github.com/PyCoWIN/
Author: Kunal Kumar Sahoo
Author-email: kunal.sahoo2003@gmail.com
License: UNKNOWN
Project-URL: Bug Reports, https://github.com/Kunal-Kumar-Sahoo/PyCowinAPI/cowin/issues
Project-URL: Source, https://github.com/Kunal-Kumar-Sahoo/PyCowinAPI/cowin
Keywords: cowin,covid,vaccine
Platform: UNKNOWN
Classifier: Environment :: Console
Classifier: License :: OSI Approved :: MIT License
Classifier: Operating System :: Unix
Classifier: Operating System :: MacOS :: MacOS X
Classifier: Operating System :: Microsoft :: Windows
Classifier: Programming Language :: Python :: 3
Classifier: Programming Language :: Python :: 3.6
Classifier: Programming Language :: Python :: 3.7
Classifier: Programming Language :: Python :: 3.8
Classifier: Programming Language :: Python :: 3.9
Classifier: Programming Language :: Python :: 3 :: Only
Requires-Python: >=3.6, <4
Requires-Dist: fake-useragent (==0.1.11)
Requires-Dist: pytest (==6.2.3)
Requires-Dist: requests (==2.25.1)
Requires-Dist: typing (==3.7.4.3)
